rwsdates/__init__.py
rwsdates/dates.py
rwsdigital_utils-2022.6.7.9.dist-info/LICENSE
rwsdigital_utils-2022.6.7.9.dist-info/METADATA
rwsdigital_utils-2022.6.7.9.dist-info/WHEEL
rwsdigital_utils-2022.6.7.9.dist-info/top_level.txt
rwsdigital_utils-2022.6.7.9.dist-info/RECORD
