Metadata-Version: 2.1
Name: rwsdigital-utils
Version: 2022.6.7.9
Summary: Odoo Development Utils by RWS Digital
Home-page: https://github.com/sCast17/rwsdigital-utils
Author: Salvatore Castaldo
Author-email: salvatore.cast17@gmail.com
License: MIT License
Classifier: Development Status :: 3 - Alpha
Classifier: Intended Audience :: Developers
Classifier: License :: OSI Approved :: MIT License
Classifier: Programming Language :: Python :: 3
Requires-Python: >=3.6
License-File: LICENSE
